{
  "<pad>": 0,
  "<sos>": 1,
  "<eos>": 2,
  "<unk>": 3,
  "!": 4,
  "\"": 5,
  "#": 6,
  "&": 7,
  "'": 8,
  "(": 9,
  ")": 10,
  "*": 11,
  "+": 12,
  ",": 13,
  "-": 14,
  "--": 15,
  "---": 16,
  ".": 17,
  "/": 18,
  "0": 19,
  "0.1": 20,
  "0.14": 21,
  "0.23": 22,
  "0.4": 23,
  "0.5": 24,
  "0.9": 25,
  "1": 26,
  "1.7": 27,
  "10": 28,
  "2": 29,
  "2.1": 30,
  "20": 31,
  "3": 32,
  "3.1": 33,
  "3.2": 34,
  "4": 35,
  "5": 36,
  "6": 37,
  "7": 38,
  "8": 39,
  "8.5": 40,
  "9": 41,
  ":": 42,
  ";": 43,
  "<": 44,
  "=": 45,
  ">": 46,
  "?": 47,
  "A": 48,
  "B": 49,
  "C": 50,
  "D": 51,
  "E": 52,
  "F": 53,
  "G": 54,
  "H": 55,
  "I": 56,
  "J": 57,
  "K": 58,
  "L": 59,
  "M": 60,
  "N": 61,
  "O": 62,
  "Object]": 63,
  "P": 64,
  "Q": 65,
  "R": 66,
  "S": 67,
  "T": 68,
  "U": 69,
  "V": 70,
  "W": 71,
  "X": 72,
  "Y": 73,
  "Z": 74,
  "[": 75,
  "[object": 76,
  "\\": 77,
  "\\!": 78,
  "\\#": 79,
  "\\&": 80,
  "\\'": 81,
  "\\*": 82,
  "\\,": 83,
  "\\-": 84,
  "\\/": 85,
  "\\:": 86,
  "\\;": 87,
  "\\AA": 88,
  "\\Big": 89,
  "\\Bigg": 90,
  "\\Biggl": 91,
  "\\Biggm": 92,
  "\\Biggr": 93,
  "\\Bigl": 94,
  "\\Bigm": 95,
  "\\Bigr": 96,
  "\\Delta": 97,
  "\\Downarrow": 98,
  "\\Gamma": 99,
  "\\Huge": 100,
  "\\Im": 101,
  "\\L": 102,
  "\\LARGE": 103,
  "\\Lambda": 104,
  "\\Large": 105,
  "\\Leftrightarrow": 106,
  "\\Longleftarrow": 107,
  "\\Longleftrightarrow": 108,
  "\\Longrightarrow": 109,
  "\\O": 110,
  "\\Omega": 111,
  "\\P": 112,
  "\\Phi": 113,
  "\\Pi": 114,
  "\\Psi": 115,
  "\\Re": 116,
  "\\Rightarrow": 117,
  "\\S": 118,
  "\\SS": 119,
  "\\Sigma": 120,
  "\\Theta": 121,
  "\\Upsilon": 122,
  "\\Vert": 123,
  "\\Xi": 124,
  "\\\\": 125,
  "\\^": 126,
  "\\_": 127,
  "\\acute": 128,
  "\\ae": 129,
  "\\aleph": 130,
  "\\alpha": 131,
  "\\amalg": 132,
  "\\approx": 133,
  "\\arraycolsep": 134,
  "\\arraystretch": 135,
  "\\arrowvert": 136,
  "\\ast": 137,
  "\\asymp": 138,
  "\\atop": 139,
  "\\atopwithdelims": 140,
  "\\b": 141,
  "\\backslash": 142,
  "\\bar": 143,
  "\\begin{array}": 144,
  "\\beta": 145,
  "\\bf": 146,
  "\\big": 147,
  "\\bigcap": 148,
  "\\bigcup": 149,
  "\\bigg": 150,
  "\\biggl": 151,
  "\\biggm": 152,
  "\\biggr": 153,
  "\\bigl": 154,
  "\\bigm": 155,
  "\\bigoplus": 156,
  "\\bigotimes": 157,
  "\\bigr": 158,
  "\\bigsqcup": 159,
  "\\bigtriangledown": 160,
  "\\bigtriangleup": 161,
  "\\bigvee": 162,
  "\\bigwedge": 163,
  "\\binom": 164,
  "\\bmod": 165,
  "\\boldmath": 166,
  "\\bot": 167,
  "\\brace": 168,
  "\\brack": 169,
  "\\breve": 170,
  "\\buildrel": 171,
  "\\bullet": 172,
  "\\c": 173,
  "\\cal": 174,
  "\\cap": 175,
  "\\cdot": 176,
  "\\cdotp": 177,
  "\\cdots": 178,
  "\\check": 179,
  "\\chi": 180,
  "\\circ": 181,
  "\\circle": 182,
  "\\cite": 183,
  "\\colon": 184,
  "\\cong": 185,
  "\\crcr": 186,
  "\\cup": 187,
  "\\d": 188,
  "\\dag": 189,
  "\\dagger": 190,
  "\\ddag": 191,
  "\\ddagger": 192,
  "\\ddot": 193,
  "\\ddots": 194,
  "\\delta": 195,
  "\\diamond": 196,
  "\\diamondsuit": 197,
  "\\displaystyle": 198,
  "\\do": 199,
  "\\dot": 200,
  "\\doteq": 201,
  "\\dots": 202,
  "\\downarrow": 203,
  "\\ell": 204,
  "\\em": 205,
  "\\emptyset": 206,
  "\\end{array}": 207,
  "\\enskip": 208,
  "\\enspace": 209,
  "\\ensuremath": 210,
  "\\epsilon": 211,
  "\\equiv": 212,
  "\\eta": 213,
  "\\exists": 214,
  "\\fbox": 215,
  "\\fboxsep": 216,
  "\\fill": 217,
  "\\flat": 218,
  "\\footnotemark": 219,
  "\\footnotesize": 220,
  "\\forall": 221,
  "\\frac": 222,
  "\\framebox": 223,
  "\\gamma": 224,
  "\\ge": 225,
  "\\geq": 226,
  "\\gg": 227,
  "\\grave": 228,
  "\\hat": 229,
  "\\hbar": 230,
  "\\hfil": 231,
  "\\hfill": 232,
  "\\hline": 233,
  "\\hookrightarrow": 234,
  "\\hphantom": 235,
  "\\hrule": 236,
  "\\hspace": 237,
  "\\hss": 238,
  "\\i": 239,
  "\\imath": 240,
  "\\in": 241,
  "\\infty": 242,
  "\\int": 243,
  "\\iota": 244,
  "\\it": 245,
  "\\itshape": 246,
  "\\j": 247,
  "\\jmath": 248,
  "\\kappa": 249,
  "\\kern": 250,
  "\\l": 251,
  "\\label": 252,
  "\\lambda": 253,
  "\\land": 254,
  "\\langle": 255,
  "\\large": 256,
  "\\lbrace": 257,
  "\\lbrack": 258,
  "\\lceil": 259,
  "\\ldots": 260,
  "\\le": 261,
  "\\leavevmode": 262,
  "\\left(": 263,
  "\\left.": 264,
  "\\left/": 265,
  "\\left<": 266,
  "\\left[": 267,
  "\\left\\langle": 268,
  "\\left\\lbrace": 269,
  "\\left\\lbrack": 270,
  "\\left\\lceil": 271,
  "\\left\\lfloor": 272,
  "\\left\\vert": 273,
  "\\left\\{": 274,
  "\\left\\|": 275,
  "\\left]": 276,
  "\\leftarrow": 277,
  "\\lefteqn": 278,
  "\\leftrightarrow": 279,
  "\\left|": 280,
  "\\leq": 281,
  "\\lfloor": 282,
  "\\lgroup": 283,
  "\\line": 284,
  "\\ll": 285,
  "\\llap": 286,
  "\\longleftarrow": 287,
  "\\longleftrightarrow": 288,
  "\\longmapsto": 289,
  "\\longrightarrow": 290,
  "\\lower": 291,
  "\\lq": 292,
  "\\m": 293,
  "\\makebox": 294,
  "\\mapsto": 295,
  "\\mathaccent": 296,
  "\\mathbf": 297,
  "\\mathbin": 298,
  "\\mathcal": 299,
  "\\mathclose": 300,
  "\\mathit": 301,
  "\\mathop": 302,
  "\\mathopen": 303,
  "\\mathord": 304,
  "\\mathrel": 305,
  "\\mathrm": 306,
  "\\mathsf": 307,
  "\\mathstrut": 308,
  "\\mathversion": 309,
  "\\medskip": 310,
  "\\mid": 311,
  "\\mit": 312,
  "\\mkern": 313,
  "\\mp": 314,
  "\\mskip": 315,
  "\\mu": 316,
  "\\multicolumn": 317,
  "\\multiput": 318,
  "\\nabla": 319,
  "\\natural": 320,
  "\\ne": 321,
  "\\nearrow": 322,
  "\\neq": 323,
  "\\newcommand": 324,
  "\\ni": 325,
  "\\noalign": 326,
  "\\nolinebreak": 327,
  "\\nonumber": 328,
  "\\normalsize": 329,
  "\\not": 330,
  "\\notin": 331,
  "\\nu": 332,
  "\\null": 333,
  "\\nulldelimiterspace": 334,
  "\\o": 335,
  "\\odot": 336,
  "\\of": 337,
  "\\oint": 338,
  "\\omega": 339,
  "\\ominus": 340,
  "\\ooalign": 341,
  "\\operatorname": 342,
  "\\operatorname*": 343,
  "\\oplus": 344,
  "\\oslash": 345,
  "\\otimes": 346,
  "\\overbrace": 347,
  "\\overleftarrow": 348,
  "\\overline": 349,
  "\\overrightarrow": 350,
  "\\overwithdelims": 351,
  "\\parallel": 352,
  "\\parbox": 353,
  "\\partial": 354,
  "\\perp": 355,
  "\\phantom": 356,
  "\\phi": 357,
  "\\pi": 358,
  "\\pm": 359,
  "\\pmod": 360,
  "\\pounds": 361,
  "\\prec": 362,
  "\\prime": 363,
  "\\prod": 364,
  "\\propto": 365,
  "\\protect": 366,
  "\\protectE": 367,
  "\\protectZ": 368,
  "\\protecte": 369,
  "\\protectm": 370,
  "\\protectu": 371,
  "\\psi": 372,
  "\\put": 373,
  "\\qquad": 374,
  "\\quad": 375,
  "\\raise": 376,
  "\\raisebox": 377,
  "\\rangle": 378,
  "\\rbrace": 379,
  "\\rbrack": 380,
  "\\ref": 381,
  "\\relax": 382,
  "\\renewcommand": 383,
  "\\rfloor": 384,
  "\\rgroup": 385,
  "\\rho": 386,
  "\\right)": 387,
  "\\right.": 388,
  "\\right/": 389,
  "\\right>": 390,
  "\\right[": 391,
  "\\right\\rangle": 392,
  "\\right\\rbrace": 393,
  "\\right\\rbrack": 394,
  "\\right\\rceil": 395,
  "\\right\\rfloor": 396,
  "\\right\\vert": 397,
  "\\right\\|": 398,
  "\\right\\}": 399,
  "\\right]": 400,
  "\\rightarrow": 401,
  "\\rightarrowfill": 402,
  "\\rightharpoonup": 403,
  "\\rightleftharpoons": 404,
  "\\right|": 405,
  "\\rlap": 406,
  "\\root": 407,
  "\\sb": 408,
  "\\sc": 409,
  "\\scriptscriptstyle": 410,
  "\\scriptsize": 411,
  "\\scriptstyle": 412,
  "\\searrow": 413,
  "\\setcounter": 414,
  "\\setlength": 415,
  "\\setminus": 416,
  "\\sf": 417,
  "\\sharp": 418,
  "\\sigma": 419,
  "\\sim": 420,
  "\\simeq": 421,
  "\\skew": 422,
  "\\sl": 423,
  "\\slash": 424,
  "\\small": 425,
  "\\smallint": 426,
  "\\smallskip": 427,
  "\\smash": 428,
  "\\smile": 429,
  "\\sp": 430,
  "\\space": 431,
  "\\special": 432,
  "\\sqcap": 433,
  "\\sqcup": 434,
  "\\sqrt": 435,
  "\\ss": 436,
  "\\stackrel": 437,
  "\\star": 438,
  "\\strut": 439,
  "\\subset": 440,
  "\\subseteq": 441,
  "\\succ": 442,
  "\\succeq": 443,
  "\\sum": 444,
  "\\supset": 445,
  "\\supseteq": 446,
  "\\surd": 447,
  "\\symbol": 448,
  "\\tau": 449,
  "\\textbf": 450,
  "\\textit": 451,
  "\\textnormal": 452,
  "\\textrm": 453,
  "\\textsf": 454,
  "\\textstyle": 455,
  "\\texttt": 456,
  "\\textup": 457,
  "\\theta": 458,
  "\\thicklines": 459,
  "\\thinspace": 460,
  "\\tilde": 461,
  "\\times": 462,
  "\\tiny": 463,
  "\\to": 464,
  "\\top": 465,
  "\\triangle": 466,
  "\\triangleleft": 467,
  "\\triangleright": 468,
  "\\tt": 469,
  "\\unboldmath": 470,
  "\\underbrace": 471,
  "\\underline": 472,
  "\\unitlength": 473,
  "\\uparrow": 474,
  "\\upsilon": 475,
  "\\varepsilon": 476,
  "\\varphi": 477,
  "\\varpi": 478,
  "\\varrho": 479,
  "\\varsigma": 480,
  "\\vartheta": 481,
  "\\vcenter": 482,
  "\\vdash": 483,
  "\\vdots": 484,
  "\\vec": 485,
  "\\vector": 486,
  "\\vee": 487,
  "\\verb": 488,
  "\\vert": 489,
  "\\vline": 490,
  "\\vphantom": 491,
  "\\vrule": 492,
  "\\vskip": 493,
  "\\vspace": 494,
  "\\vss": 495,
  "\\wedge": 496,
  "\\widehat": 497,
  "\\widetilde": 498,
  "\\wp": 499,
  "\\xi": 500,
  "\\zeta": 501,
  "\\{": 502,
  "\\|": 503,
  "\\}": 504,
  "]": 505,
  "^": 506,
  "_": 507,
  "`": 508,
  "a": 509,
  "b": 510,
  "c": 511,
  "cm": 512,
  "d": 513,
  "e": 514,
  "f": 515,
  "g": 516,
  "h": 517,
  "i": 518,
  "in": 519,
  "j": 520,
  "k": 521,
  "l": 522,
  "m": 523,
  "mm": 524,
  "n": 525,
  "o": 526,
  "p": 527,
  "pt": 528,
  "q": 529,
  "r": 530,
  "s": 531,
  "t": 532,
  "u": 533,
  "ule": 534,
  "v": 535,
  "w": 536,
  "x": 537,
  "y": 538,
  "z": 539,
  "{": 540,
  "|": 541,
  "}": 542,
  "~": 543
}